MANIFEST.in
README.md
setup.py
testoot/__init__.py
testoot/base.py
testoot/base_testoot.py
testoot/exceptions.py
testoot/policies.py
testoot/pub.py
testoot/serializers.py
testoot/storages.py
testoot/testoot.py
testoot/user_interactions.py
testoot.egg-info/PKG-INFO
testoot.egg-info/SOURCES.txt
testoot.egg-info/dependency_links.txt
testoot.egg-info/top_level.txt
testoot/ext/__init__.py
testoot/ext/pytest.py
testoot/ext/simple.py