Metadata-Version: 2.1
Name: testoot
Version: 0.0.5
Summary: Library
Home-page: https://github.com/aptakhin/testoot
Author: Alexander Ptakhin
Author-email: me@aptakhin.name
License: MIT
Project-URL: Source Code, https://github.com/aptakhin/testoot
Keywords: testing out of code
Platform: UNKNOWN
Classifier: Development Status :: 3 - Alpha
Classifier: Intended Audience :: Developers
Classifier: License :: OSI Approved :: MIT License
Classifier: Programming Language :: Python
Classifier: Topic :: Software Development
Classifier: Framework :: Pytest
Classifier: Topic :: Software Development :: Testing
Classifier: Topic :: Software Development :: Quality Assurance
Classifier: Topic :: Software Development :: Testing :: Unit
